README.md
setup.py
ptcaffe_plugins/__init__.py
ptcaffe_plugins.egg-info/PKG-INFO
ptcaffe_plugins.egg-info/SOURCES.txt
ptcaffe_plugins.egg-info/dependency_links.txt
ptcaffe_plugins.egg-info/requires.txt
ptcaffe_plugins.egg-info/top_level.txt
ptcaffe_plugins/deeplab/__init__.py
ptcaffe_plugins/deeplab/image_seg_data_layer.py
ptcaffe_plugins/deeplab/interp_layer.py
ptcaffe_plugins/deeplab/seg_accuracy_layer.py
ptcaffe_plugins/deeplab/seg_evaluator_layer.py
ptcaffe_plugins/deeplab/vocdata_layer.py
ptcaffe_plugins/fcn/__init__.py
ptcaffe_plugins/fcn/data_layers.py
ptcaffe_plugins/fcn/score_evaluator_layer.py
ptcaffe_plugins/ssd/__init__.py
ptcaffe_plugins/ssd/annotated_data_layer.py
ptcaffe_plugins/ssd/augmentations.py
ptcaffe_plugins/ssd/bbox_utils.py
ptcaffe_plugins/ssd/detection_evaluation2_layer.py
ptcaffe_plugins/ssd/detection_evaluation_layer.py
ptcaffe_plugins/ssd/detection_output_layer.py
ptcaffe_plugins/ssd/multibox_loss_layer.py
ptcaffe_plugins/ssd/ssdlist_data_layer.py
ptcaffe_plugins/ssd/voc_detection.py
ptcaffe_plugins/yolo/__init__.py
ptcaffe_plugins/yolo/data_layer.py
ptcaffe_plugins/yolo/eval_layers.py
ptcaffe_plugins/yolo/image.py
ptcaffe_plugins/yolo/label_convert.py
ptcaffe_plugins/yolo/region_loss.py
ptcaffe_plugins/yolo/reorg_layer.py
ptcaffe_plugins/yolo/upsample_layer.py
ptcaffe_plugins/yolo/utils.py
ptcaffe_plugins/yolo/voc_eval.py
ptcaffe_plugins/yolo/yolo_loss.py