Metadata-Version: 1.0
Name: ptcaffe-plugins
Version: 1.0.0
Summary: ptcaffe plugins
Home-page: http://github.com/marvis
Author: xiaohang
Author-email: UNKNOWN
License: MIT Licence
Platform: any
